dockerctl.py
dockerctl/__init__.py
dockerctl/actions.py
dockerctl/executor.py
dockerctl/help_page.py
dockerctl/parser.py
dockerctl-1.2.data/scripts/dockerctl
dockerctl-1.2.dist-info/licenses/LICENSE
dockerctl-1.2.dist-info/METADATA
dockerctl-1.2.dist-info/WHEEL
dockerctl-1.2.dist-info/top_level.txt
dockerctl-1.2.dist-info/RECORD
