Metadata-Version: 2.4
Name: dockerctl
Version: 1.2
Summary: Python Script to steer (multiple) docker-compose-yaml's from everywhere.
Home-page: https://github.com/bionade24/dockerctl
Author: Oskar Roesler (bionade24)
Author-email: o.roesler@oscloud.info
License: GPLv3
Classifier: Development Status :: 5 - Production/Stable
Classifier: License :: OSI Approved :: GNU General Public License v3 (GPLv3)
Classifier: Programming Language :: Python :: 3
Classifier: Operating System :: POSIX :: Linux
License-File: LICENSE
Dynamic: author
Dynamic: author-email
Dynamic: classifier
Dynamic: description
Dynamic: description-content-type
Dynamic: home-page
Dynamic: license
Dynamic: license-file
Dynamic: summary
